refcycle/__init__.py
refcycle/annotated_graph.py
refcycle/annotations.py
refcycle/creators.py
refcycle/directed_graph.py
refcycle/element_transform_set.py
refcycle/gc_utils.py
refcycle/i_directed_graph.py
refcycle/key_transform_dict.py
refcycle/object_graph.py
refcycle/test/__init__.py
refcycle/test/test_annotated_graph.py
refcycle/test/test_annotations.py
refcycle/test/test_directed_graph.py
refcycle/test/test_element_transform_set.py
refcycle/test/test_key_transform_dict.py
refcycle/test/test_object_graph.py
refcycle/test/test_refcycle.py
refcycle-0.3.1.dist-info/LICENSE
refcycle-0.3.1.dist-info/METADATA
refcycle-0.3.1.dist-info/WHEEL
refcycle-0.3.1.dist-info/top_level.txt
refcycle-0.3.1.dist-info/RECORD
