Metadata-Version: 2.1
Name: refcycle
Version: 0.3.1
Summary: Find and visualise reference cycles between Python objects
Author-email: Mark Dickinson <dickinsm@gmail.com>
License: 
Project-URL: Homepage, https://github.com/mdickinson/refcycle
Project-URL: Documentation, https://refcycle.readthedocs.io/
Keywords: cycle,cyclic,debugging,garbage,graph,reference
Classifier: Development Status :: 4 - Beta
Classifier: Intended Audience :: Developers
Classifier: License :: OSI Approved :: Apache Software License
Classifier: Operating System :: OS Independent
Classifier: Programming Language :: Python :: 3
Classifier: Programming Language :: Python :: Implementation :: CPython
Classifier: Topic :: Software Development :: Debuggers
Requires-Python: >=3.7
License-File: LICENSE
